[
  {
    "event": "50 FR SCY",
    "swimTime": "32.24",
    "age": "10",
    "points": "495",
    "timeStandard": "BB",
    "meet": "2025 NT LAC Splashing Pumpkins",
    "lsc": "NT",
    "team": "Lakeside Aquatic Club",
    "swimDate": "10/04/2025",
    "competitionYear": "-1"
  },
  {
    "event": "50 FR SCY",
    "swimTime": "34.54",
    "age": "10",
    "points": "368",
    "timeStandard": "BB",
    "meet": "2025 NT LAC Heart Racer",
    "lsc": "NT",
    "team": "Lakeside Aquatic Club",
    "swimDate": "02/16/2025",
    "competitionYear": "-1"
  },
  {
    "event": "50 FR SCY",
    "swimTime": "35.22",
    "age": "9",
    "points": "446",
    "timeStandard": "B",
    "meet": "2024 NT LAC Splashing Pumpkins",
    "lsc": "NT",
    "team": "Lakeside Aquatic Club",
    "swimDate": "10/06/2024",
    "competitionYear": "-1"
  },
  {
    "event": "50 FR SCY",
    "swimTime": "35.82",
    "age": "9",
    "points": "415",
    "timeStandard": "B",
    "meet": "2024 NT LAC A-Maize-ing Autumn Meet",
    "lsc": "NT",
    "team": "Lakeside Aquatic Club",
    "swimDate": "11/10/2024",
    "competitionYear": "-1"
  },
  {
    "event": "50 FR SCY",
    "swimTime": "37.31",
    "age": "9",
    "points": "340",
    "timeStandard": "2020-2024 B",
    "meet": "2024 NT LAC Season Opener",
    "lsc": "NT",
    "team": "Lakeside Aquatic Club",
    "swimDate": "04/13/2024",
    "competitionYear": "-1"
  },
  {
    "event": "50 FR SCY",
    "swimTime": "37.92",
    "age": "9",
    "points": "310",
    "timeStandard": "2020-2024 B",
    "meet": "2024 NT LAC May Madness Meet",
    "lsc": "NT",
    "team": "Lakeside Aquatic Club",
    "swimDate": "05/05/2024",
    "competitionYear": "-1"
  },
  {
    "event": "50 FR SCY",
    "swimTime": "38.34",
    "age": "8",
    "points": "290",
    "timeStandard": "Slower than B",
    "meet": "2023 NT LAC Jingle Bell Meet",
    "lsc": "NT",
    "team": "Lakeside Aquatic Club",
    "swimDate": "12/09/2023",
    "competitionYear": "-1"
  },
  {
    "event": "50 FR SCY",
    "swimTime": "38.39",
    "age": "8",
    "points": "288",
    "timeStandard": "Slower than B",
    "meet": "2023 NT LAC Spooky Splash Intrasquad Meet",
    "lsc": "NT",
    "team": "Lakeside Aquatic Club",
    "swimDate": "10/22/2023",
    "competitionYear": "-1"
  },
  {
    "event": "50 FR SCY",
    "swimTime": "39.03",
    "age": "8",
    "points": "258",
    "timeStandard": "Slower than B",
    "meet": "2023 NT LAC Summer Sweater",
    "lsc": "NT",
    "team": "Lakeside Aquatic Club",
    "swimDate": "07/22/2023",
    "competitionYear": "-1"
  },
  {
    "event": "50 FR SCY",
    "swimTime": "41.97",
    "age": "8",
    "points": "131",
    "timeStandard": "Slower than B",
    "meet": "2023 NT LAC Summer Sizzler",
    "lsc": "NT",
    "team": "Lakeside Aquatic Club",
    "swimDate": "06/03/2023",
    "competitionYear": "-1"
  },
  {
    "event": "100 FR SCY",
    "swimTime": "1:13.25",
    "age": "10",
    "points": "382",
    "timeStandard": "BB",
    "meet": "2025 NT LAC Splashing Pumpkins",
    "lsc": "NT",
    "team": "Lakeside Aquatic Club",
    "swimDate": "10/05/2025",
    "competitionYear": "-1"
  },
  {
    "event": "100 FR SCY",
    "swimTime": "1:15.88",
    "age": "10",
    "points": "315",
    "timeStandard": "BB",
    "meet": "2025 NT STAR We Love Flip Turns Meet",
    "lsc": "NT",
    "team": "Lakeside Aquatic Club",
    "swimDate": "06/15/2025",
    "competitionYear": "-1"
  },
  {
    "event": "100 FR SCY",
    "swimTime": "1:20.47",
    "age": "10",
    "points": "209",
    "timeStandard": "B",
    "meet": "2024 NT LAC Jingle Bell",
    "lsc": "NT",
    "team": "Lakeside Aquatic Club",
    "swimDate": "12/15/2024",
    "competitionYear": "-1"
  },
  {
    "event": "100 FR SCY",
    "swimTime": "1:24.16",
    "age": "8",
    "points": "256",
    "timeStandard": "2020-2024 B",
    "meet": "2023 NT LAC Spooky Splash Intrasquad Meet",
    "lsc": "NT",
    "team": "Lakeside Aquatic Club",
    "swimDate": "10/22/2023",
    "competitionYear": "-1"
  },
  {
    "event": "100 FR SCY",
    "swimTime": "1:24.62",
    "age": "8",
    "points": "246",
    "timeStandard": "2020-2024 B",
    "meet": "2023 NT LAC Summer Sweater",
    "lsc": "NT",
    "team": "Lakeside Aquatic Club",
    "swimDate": "07/21/2023",
    "competitionYear": "-1"
  },
  {
    "event": "100 FR SCY",
    "swimTime": "1:25.03",
    "age": "9",
    "points": "237",
    "timeStandard": "2020-2024 B",
    "meet": "2024 NT LAC Season Opener",
    "lsc": "NT",
    "team": "Lakeside Aquatic Club",
    "swimDate": "04/14/2024",
    "competitionYear": "-1"
  },
  {
    "event": "100 FR SCY",
    "swimTime": "1:25.81",
    "age": "9",
    "points": "221",
    "timeStandard": "2020-2024 B",
    "meet": "2024 NT LAC Ice Breaker",
    "lsc": "NT",
    "team": "Lakeside Aquatic Club",
    "swimDate": "01/06/2024",
    "competitionYear": "-1"
  },
  {
    "event": "100 FR SCY",
    "swimTime": "1:30.79",
    "age": "8",
    "points": "128",
    "timeStandard": "Slower than B",
    "meet": "2023 NT LAC Summer Sizzler",
    "lsc": "NT",
    "team": "Lakeside Aquatic Club",
    "swimDate": "06/02/2023",
    "competitionYear": "-1"
  },
  {
    "event": "200 FR SCY",
    "swimTime": "2:32.37",
    "age": "10",
    "points": "437",
    "timeStandard": "BB",
    "meet": "2025 NT LAC Splashing Pumpkins",
    "lsc": "NT",
    "team": "Lakeside Aquatic Club",
    "swimDate": "10/04/2025",
    "competitionYear": "-1"
  },
  {
    "event": "200 FR SCY",
    "swimTime": "3:05.02",
    "age": "8",
    "points": "204",
    "timeStandard": "2020-2024 B",
    "meet": "2023 NT LAC Jingle Bell Meet",
    "lsc": "NT",
    "team": "Lakeside Aquatic Club",
    "swimDate": "12/09/2023",
    "competitionYear": "-1"
  },
  {
    "event": "500 FR SCY",
    "swimTime": "7:21.91",
    "age": "10",
    "points": "276",
    "timeStandard": "BB",
    "meet": "2025 NT STAR We Love Flip Turns Meet",
    "lsc": "NT",
    "team": "Lakeside Aquatic Club",
    "swimDate": "06/15/2025",
    "competitionYear": "-1"
  },
  {
    "event": "50 BK SCY",
    "swimTime": "35.96",
    "age": "10",
    "points": "552",
    "timeStandard": "A",
    "meet": "2025 NT LAC Splashing Pumpkins",
    "lsc": "NT",
    "team": "Lakeside Aquatic Club",
    "swimDate": "10/04/2025",
    "competitionYear": "-1"
  },
  {
    "event": "50 BK SCY",
    "swimTime": "39.82",
    "age": "10",
    "points": "353",
    "timeStandard": "BB",
    "meet": "2024 NT LAC Jingle Bell",
    "lsc": "NT",
    "team": "Lakeside Aquatic Club",
    "swimDate": "12/15/2024",
    "competitionYear": "-1"
  },
  {
    "event": "50 BK SCY",
    "swimTime": "41.06",
    "age": "9",
    "points": "421",
    "timeStandard": "BB",
    "meet": "2024 NT LAC Splashing Pumpkins",
    "lsc": "NT",
    "team": "Lakeside Aquatic Club",
    "swimDate": "10/05/2024",
    "competitionYear": "-1"
  },
  {
    "event": "50 BK SCY",
    "swimTime": "42.28",
    "age": "9",
    "points": "365",
    "timeStandard": "2020-2024 BB",
    "meet": "2024 NT LAC Ice Breaker",
    "lsc": "NT",
    "team": "Lakeside Aquatic Club",
    "swimDate": "01/06/2024",
    "competitionYear": "-1"
  },
  {
    "event": "50 BK SCY",
    "swimTime": "42.30",
    "age": "9",
    "points": "364",
    "timeStandard": "2020-2024 B",
    "meet": "2024 NT LAC Season Opener",
    "lsc": "NT",
    "team": "Lakeside Aquatic Club",
    "swimDate": "04/14/2024",
    "competitionYear": "-1"
  },
  {
    "event": "50 BK SCY",
    "swimTime": "42.95",
    "age": "8",
    "points": "335",
    "timeStandard": "2020-2024 B",
    "meet": "2023 NT LAC Jingle Bell Meet",
    "lsc": "NT",
    "team": "Lakeside Aquatic Club",
    "swimDate": "12/10/2023",
    "competitionYear": "-1"
  },
  {
    "event": "50 BK SCY",
    "swimTime": "43.07",
    "age": "8",
    "points": "330",
    "timeStandard": "2020-2024 B",
    "meet": "2023 NT LAC Summer Sweater",
    "lsc": "NT",
    "team": "Lakeside Aquatic Club",
    "swimDate": "07/21/2023",
    "competitionYear": "-1"
  },
  {
    "event": "50 BK SCY",
    "swimTime": "43.53",
    "age": "8",
    "points": "310",
    "timeStandard": "2020-2024 B",
    "meet": "2023 NT LAC Spooky Splash Intrasquad Meet",
    "lsc": "NT",
    "team": "Lakeside Aquatic Club",
    "swimDate": "10/22/2023",
    "competitionYear": "-1"
  },
  {
    "event": "50 BK SCY",
    "swimTime": "48.14",
    "age": "8",
    "points": "135",
    "timeStandard": "Slower than B",
    "meet": "2023 NT LAC Summer Sizzler",
    "lsc": "NT",
    "team": "Lakeside Aquatic Club",
    "swimDate": "06/02/2023",
    "competitionYear": "-1"
  },
  {
    "event": "100 BK SCY",
    "swimTime": "1:17.21",
    "age": "10",
    "points": "550",
    "timeStandard": "A",
    "meet": "2025 NT LAC Splashing Pumpkins",
    "lsc": "NT",
    "team": "Lakeside Aquatic Club",
    "swimDate": "10/05/2025",
    "competitionYear": "-1"
  },
  {
    "event": "100 BK SCY",
    "swimTime": "1:21.29",
    "age": "10",
    "points": "448",
    "timeStandard": "BB",
    "meet": "2025 NT LAC Heart Racer",
    "lsc": "NT",
    "team": "Lakeside Aquatic Club",
    "swimDate": "02/16/2025",
    "competitionYear": "-1"
  },
  {
    "event": "100 BK SCY",
    "swimTime": "1:23.32",
    "age": "10",
    "points": "400",
    "timeStandard": "BB",
    "meet": "2024 NT LAC Jingle Bell",
    "lsc": "NT",
    "team": "Lakeside Aquatic Club",
    "swimDate": "12/14/2024",
    "competitionYear": "-1"
  },
  {
    "event": "100 BK SCY",
    "swimTime": "1:31.05",
    "age": "9",
    "points": "361",
    "timeStandard": "2020-2024 B",
    "meet": "2024 NT LAC May Madness Meet",
    "lsc": "NT",
    "team": "Lakeside Aquatic Club",
    "swimDate": "05/05/2024",
    "competitionYear": "-1"
  },
  {
    "event": "100 BK SCY",
    "swimTime": "1:31.37",
    "age": "9",
    "points": "355",
    "timeStandard": "2020-2024 B",
    "meet": "2024 NT LAC Heart Racer",
    "lsc": "NT",
    "team": "Lakeside Aquatic Club",
    "swimDate": "02/04/2024",
    "competitionYear": "-1"
  },
  {
    "event": "100 BK SCY",
    "swimTime": "1:33.48",
    "age": "8",
    "points": "312",
    "timeStandard": "2020-2024 B",
    "meet": "2023 NT LAC Spooky Splash Intrasquad Meet",
    "lsc": "NT",
    "team": "Lakeside Aquatic Club",
    "swimDate": "10/21/2023",
    "competitionYear": "-1"
  },
  {
    "event": "100 BK SCY",
    "swimTime": "1:33.82",
    "age": "9",
    "points": "305",
    "timeStandard": "2020-2024 B",
    "meet": "2024 NT LAC Ice Breaker",
    "lsc": "NT",
    "team": "Lakeside Aquatic Club",
    "swimDate": "01/07/2024",
    "competitionYear": "-1"
  },
  {
    "event": "100 BK SCY",
    "swimTime": "1:48.63",
    "age": "8",
    "points": "65",
    "timeStandard": "Slower than B",
    "meet": "2023 NT LAC Summer Sizzler",
    "lsc": "NT",
    "team": "Lakeside Aquatic Club",
    "swimDate": "06/03/2023",
    "competitionYear": "-1"
  },
  {
    "event": "50 BR SCY",
    "swimTime": "46.67",
    "age": "9",
    "points": "403",
    "timeStandard": "BB",
    "meet": "2024 NT LAC Splashing Pumpkins",
    "lsc": "NT",
    "team": "Lakeside Aquatic Club",
    "swimDate": "10/05/2024",
    "competitionYear": "-1"
  },
  {
    "event": "50 BR SCY",
    "swimTime": "47.02",
    "age": "10",
    "points": "247",
    "timeStandard": "BB",
    "meet": "2024 NT LAC Jingle Bell",
    "lsc": "NT",
    "team": "Lakeside Aquatic Club",
    "swimDate": "12/14/2024",
    "competitionYear": "-1"
  },
  {
    "event": "50 BR SCY",
    "swimTime": "47.94",
    "age": "10",
    "points": "213",
    "timeStandard": "B",
    "meet": "2025 NT STAR We Love Flip Turns Meet",
    "lsc": "NT",
    "team": "Lakeside Aquatic Club",
    "swimDate": "06/15/2025",
    "competitionYear": "-1"
  },
  {
    "event": "50 BR SCY",
    "swimTime": "48.88",
    "age": "8",
    "points": "315",
    "timeStandard": "2020-2024 B",
    "meet": "2023 NT LAC Jingle Bell Meet",
    "lsc": "NT",
    "team": "Lakeside Aquatic Club",
    "swimDate": "12/09/2023",
    "competitionYear": "-1"
  },
  {
    "event": "50 BR SCY",
    "swimTime": "49.22",
    "age": "9",
    "points": "302",
    "timeStandard": "2020-2024 B",
    "meet": "2024 NT LAC Season Opener",
    "lsc": "NT",
    "team": "Lakeside Aquatic Club",
    "swimDate": "04/13/2024",
    "competitionYear": "-1"
  },
  {
    "event": "50 BR SCY",
    "swimTime": "49.46",
    "age": "9",
    "points": "293",
    "timeStandard": "2020-2024 B",
    "meet": "2024 NT LAC Ice Breaker",
    "lsc": "NT",
    "team": "Lakeside Aquatic Club",
    "swimDate": "01/06/2024",
    "competitionYear": "-1"
  },
  {
    "event": "50 BR SCY",
    "swimTime": "54.93",
    "age": "8",
    "points": "115",
    "timeStandard": "Slower than B",
    "meet": "2023 NT LAC Summer Sweater",
    "lsc": "NT",
    "team": "Lakeside Aquatic Club",
    "swimDate": "07/21/2023",
    "competitionYear": "-1"
  },
  {
    "event": "100 BR SCY",
    "swimTime": "1:40.33",
    "age": "10",
    "points": "289",
    "timeStandard": "BB",
    "meet": "2024 NT LAC Jingle Bell",
    "lsc": "NT",
    "team": "Lakeside Aquatic Club",
    "swimDate": "12/15/2024",
    "competitionYear": "-1"
  },
  {
    "event": "100 BR SCY",
    "swimTime": "1:40.47",
    "age": "10",
    "points": "286",
    "timeStandard": "BB",
    "meet": "2025 NT LAC Heart Racer",
    "lsc": "NT",
    "team": "Lakeside Aquatic Club",
    "swimDate": "02/16/2025",
    "competitionYear": "-1"
  },
  {
    "event": "100 BR SCY",
    "swimTime": "1:44.58",
    "age": "9",
    "points": "369",
    "timeStandard": "2020-2024 B",
    "meet": "2024 NT LAC May Madness Meet",
    "lsc": "NT",
    "team": "Lakeside Aquatic Club",
    "swimDate": "05/05/2024",
    "competitionYear": "-1"
  },
  {
    "event": "100 BR SCY",
    "swimTime": "1:45.22",
    "age": "9",
    "points": "358",
    "timeStandard": "2020-2024 B",
    "meet": "2024 NT LAC Season Opener",
    "lsc": "NT",
    "team": "Lakeside Aquatic Club",
    "swimDate": "04/14/2024",
    "competitionYear": "-1"
  },
  {
    "event": "100 BR SCY",
    "swimTime": "1:49.72",
    "age": "8",
    "points": "280",
    "timeStandard": "2020-2024 B",
    "meet": "2023 NT LAC Spooky Splash Intrasquad Meet",
    "lsc": "NT",
    "team": "Lakeside Aquatic Club",
    "swimDate": "10/21/2023",
    "competitionYear": "-1"
  },
  {
    "event": "100 BR SCY",
    "swimTime": "1:51.04",
    "age": "8",
    "points": "258",
    "timeStandard": "2020-2024 B",
    "meet": "2023 NT LAC Jingle Bell Meet",
    "lsc": "NT",
    "team": "Lakeside Aquatic Club",
    "swimDate": "12/10/2023",
    "competitionYear": "-1"
  },
  {
    "event": "100 BR SCY",
    "swimTime": "1:51.49",
    "age": "9",
    "points": "251",
    "timeStandard": "2020-2024 B",
    "meet": "2024 NT LAC Ice Breaker",
    "lsc": "NT",
    "team": "Lakeside Aquatic Club",
    "swimDate": "01/07/2024",
    "competitionYear": "-1"
  },
  {
    "event": "100 BR SCY",
    "swimTime": "1:52.51",
    "age": "9",
    "points": "235",
    "timeStandard": "2020-2024 B",
    "meet": "2024 NT LAC Heart Racer",
    "lsc": "NT",
    "team": "Lakeside Aquatic Club",
    "swimDate": "02/04/2024",
    "competitionYear": "-1"
  },
  {
    "event": "50 FL SCY",
    "swimTime": "41.71",
    "age": "9",
    "points": "282",
    "timeStandard": "B",
    "meet": "2024 NT LAC A-Maize-ing Autumn Meet",
    "lsc": "NT",
    "team": "Lakeside Aquatic Club",
    "swimDate": "11/10/2024",
    "competitionYear": "-1"
  },
  {
    "event": "50 FL SCY",
    "swimTime": "42.33",
    "age": "10",
    "points": "127",
    "timeStandard": "B",
    "meet": "2025 NT STAR We Love Flip Turns Meet",
    "lsc": "NT",
    "team": "Lakeside Aquatic Club",
    "swimDate": "06/15/2025",
    "competitionYear": "-1"
  },
  {
    "event": "50 FL SCY",
    "swimTime": "42.57",
    "age": "9",
    "points": "245",
    "timeStandard": "B",
    "meet": "2024 NT LAC Splashing Pumpkins",
    "lsc": "NT",
    "team": "Lakeside Aquatic Club",
    "swimDate": "10/06/2024",
    "competitionYear": "-1"
  },
  {
    "event": "50 FL SCY",
    "swimTime": "46.05",
    "age": "9",
    "points": "115",
    "timeStandard": "Slower than B",
    "meet": "2024 NT LAC Heart Racer",
    "lsc": "NT",
    "team": "Lakeside Aquatic Club",
    "swimDate": "02/04/2024",
    "competitionYear": "-1"
  },
  {
    "event": "50 FL SCY",
    "swimTime": "47.40",
    "age": "8",
    "points": "75",
    "timeStandard": "Slower than B",
    "meet": "2023 NT LAC Jingle Bell Meet",
    "lsc": "NT",
    "team": "Lakeside Aquatic Club",
    "swimDate": "12/10/2023",
    "competitionYear": "-1"
  },
  {
    "event": "50 FL SCY",
    "swimTime": "52.52",
    "age": "8",
    "points": "1",
    "timeStandard": "Slower than B",
    "meet": "2023 NT LAC Summer Sweater",
    "lsc": "NT",
    "team": "Lakeside Aquatic Club",
    "swimDate": "07/22/2023",
    "competitionYear": "-1"
  },
  {
    "event": "50 FL SCY",
    "swimTime": "57.64",
    "age": "8",
    "points": "1",
    "timeStandard": "Slower than B",
    "meet": "2023 NT LAC Summer Sizzler",
    "lsc": "NT",
    "team": "Lakeside Aquatic Club",
    "swimDate": "06/03/2023",
    "competitionYear": "-1"
  },
  {
    "event": "100 FL SCY",
    "swimTime": "1:34.29",
    "age": "10",
    "points": "182",
    "timeStandard": "BB",
    "meet": "2024 NT LAC Jingle Bell",
    "lsc": "NT",
    "team": "Lakeside Aquatic Club",
    "swimDate": "12/14/2024",
    "competitionYear": "-1"
  },
  {
    "event": "100 IM SCY",
    "swimTime": "1:22.34",
    "age": "10",
    "points": "406",
    "timeStandard": "BB",
    "meet": "2025 NT LAC Splashing Pumpkins",
    "lsc": "NT",
    "team": "Lakeside Aquatic Club",
    "swimDate": "10/05/2025",
    "competitionYear": "-1"
  },
  {
    "event": "100 IM SCY",
    "swimTime": "1:27.94",
    "age": "10",
    "points": "276",
    "timeStandard": "BB",
    "meet": "2025 NT STAR We Love Flip Turns Meet",
    "lsc": "NT",
    "team": "Lakeside Aquatic Club",
    "swimDate": "06/15/2025",
    "competitionYear": "-1"
  },
  {
    "event": "100 IM SCY",
    "swimTime": "1:28.41",
    "age": "9",
    "points": "403",
    "timeStandard": "BB",
    "meet": "2024 NT LAC A-Maize-ing Autumn Meet",
    "lsc": "NT",
    "team": "Lakeside Aquatic Club",
    "swimDate": "11/10/2024",
    "competitionYear": "-1"
  },
  {
    "event": "100 IM SCY",
    "swimTime": "1:30.00",
    "age": "9",
    "points": "367",
    "timeStandard": "B",
    "meet": "2024 NT LAC Splashing Pumpkins",
    "lsc": "NT",
    "team": "Lakeside Aquatic Club",
    "swimDate": "10/06/2024",
    "competitionYear": "-1"
  },
  {
    "event": "100 IM SCY",
    "swimTime": "1:38.10",
    "age": "9",
    "points": "205",
    "timeStandard": "2020-2024 B",
    "meet": "2024 NT LAC Ice Breaker",
    "lsc": "NT",
    "team": "Lakeside Aquatic Club",
    "swimDate": "01/07/2024",
    "competitionYear": "-1"
  },
  {
    "event": "100 IM SCY",
    "swimTime": "1:41.34",
    "age": "8",
    "points": "152",
    "timeStandard": "Slower than B",
    "meet": "2023 NT LAC Spooky Splash Intrasquad Meet",
    "lsc": "NT",
    "team": "Lakeside Aquatic Club",
    "swimDate": "10/21/2023",
    "competitionYear": "-1"
  },
  {
    "event": "100 IM SCY",
    "swimTime": "1:42.88",
    "age": "8",
    "points": "129",
    "timeStandard": "Slower than B",
    "meet": "2023 NT LAC Summer Sweater",
    "lsc": "NT",
    "team": "Lakeside Aquatic Club",
    "swimDate": "07/22/2023",
    "competitionYear": "-1"
  },
  {
    "event": "200 IM SCY",
    "swimTime": "3:04.16",
    "age": "10",
    "points": "327",
    "timeStandard": "BB",
    "meet": "2025 NT LAC Heart Racer",
    "lsc": "NT",
    "team": "Lakeside Aquatic Club",
    "swimDate": "02/14/2025",
    "competitionYear": "-1"
  },
  {
    "event": "200 IM SCY",
    "swimTime": "3:22.30",
    "age": "9",
    "points": "276",
    "timeStandard": "2020-2024 B",
    "meet": "2024 NT LAC Heart Racer",
    "lsc": "NT",
    "team": "Lakeside Aquatic Club",
    "swimDate": "02/02/2024",
    "competitionYear": "-1"
  },
  {
    "event": "50 FR LCM",
    "swimTime": "35.06",
    "age": "10",
    "points": "597",
    "timeStandard": "A",
    "meet": "2025 NT Texas Age Group Long Course Time Trials",
    "lsc": "NT",
    "team": "Lakeside Aquatic Club",
    "swimDate": "07/18/2025",
    "competitionYear": "-1"
  },
  {
    "event": "50 FR LCM",
    "swimTime": "36.55",
    "age": "10",
    "points": "521",
    "timeStandard": "BB",
    "meet": "2025 NT North Texas Long Course Age Group Championship",
    "lsc": "NT",
    "team": "Lakeside Aquatic Club",
    "swimDate": "06/27/2025",
    "competitionYear": "-1"
  },
  {
    "event": "50 FR LCM",
    "swimTime": "37.14",
    "age": "10",
    "points": "492",
    "timeStandard": "BB",
    "meet": "2025 NT STAR April A/BB East Division Meet",
    "lsc": "NT",
    "team": "Lakeside Aquatic Club",
    "swimDate": "04/26/2025",
    "competitionYear": "-1"
  },
  {
    "event": "50 FR LCM",
    "swimTime": "37.70",
    "age": "10",
    "points": "464",
    "timeStandard": "BB",
    "meet": "2025 NT STAR April Long Course No Bulkhead, No Problem Open",
    "lsc": "NT",
    "team": "Lakeside Aquatic Club",
    "swimDate": "04/05/2025",
    "competitionYear": "-1"
  },
  {
    "event": "50 FR LCM",
    "swimTime": "37.88",
    "age": "10",
    "points": "455",
    "timeStandard": "BB",
    "meet": "2025 NT LAC Hiroto Kobukai Memorial Invite",
    "lsc": "NT",
    "team": "Lakeside Aquatic Club",
    "swimDate": "05/18/2025",
    "competitionYear": "-1"
  },
  {
    "event": "50 FR LCM",
    "swimTime": "40.16",
    "age": "9",
    "points": "451",
    "timeStandard": "2020-2024 B",
    "meet": "2024 NT LAC Fun in the Sun",
    "lsc": "NT",
    "team": "Lakeside Aquatic Club",
    "swimDate": "07/06/2024",
    "competitionYear": "-1"
  },
  {
    "event": "100 FR LCM",
    "swimTime": "1:17.14r",
    "age": "10",
    "points": "547",
    "timeStandard": "A",
    "meet": "2025 NT Texas Age Group Long Course Championships",
    "lsc": "NT",
    "team": "Lakeside Aquatic Club",
    "swimDate": "07/18/2025",
    "competitionYear": "-1"
  },
  {
    "event": "100 FR LCM",
    "swimTime": "1:17.41",
    "age": "10",
    "points": "540",
    "timeStandard": "A",
    "meet": "2025 NT North Texas Long Course Age Group Championship",
    "lsc": "NT",
    "team": "Lakeside Aquatic Club",
    "swimDate": "06/29/2025",
    "competitionYear": "-1"
  },
  {
    "event": "100 FR LCM",
    "swimTime": "1:17.92",
    "age": "10",
    "points": "527",
    "timeStandard": "A",
    "meet": "2025 NT North Texas Long Course Age Group Championship",
    "lsc": "NT",
    "team": "Lakeside Aquatic Club",
    "swimDate": "06/29/2025",
    "competitionYear": "-1"
  },
  {
    "event": "100 FR LCM",
    "swimTime": "1:22.01",
    "age": "10",
    "points": "425",
    "timeStandard": "BB",
    "meet": "2025 NT STAR April A/BB East Division Meet",
    "lsc": "NT",
    "team": "Lakeside Aquatic Club",
    "swimDate": "04/27/2025",
    "competitionYear": "-1"
  },
  {
    "event": "100 FR LCM",
    "swimTime": "1:30.02",
    "age": "9",
    "points": "369",
    "timeStandard": "2020-2024 BB",
    "meet": "2024 NT LAC Fun in the Sun",
    "lsc": "NT",
    "team": "Lakeside Aquatic Club",
    "swimDate": "07/07/2024",
    "competitionYear": "-1"
  },
  {
    "event": "200 FR LCM",
    "swimTime": "2:48.33",
    "age": "10",
    "points": "504",
    "timeStandard": "A",
    "meet": "2025 NT TFA Quacken A & Above",
    "lsc": "NT",
    "team": "Lakeside Aquatic Club",
    "swimDate": "07/26/2025",
    "competitionYear": "-1"
  },
  {
    "event": "400 FR LCM",
    "swimTime": "6:07.85",
    "age": "10",
    "points": "453",
    "timeStandard": "BB",
    "meet": "2025 NT TFA Quacken A & Above",
    "lsc": "NT",
    "team": "Lakeside Aquatic Club",
    "swimDate": "07/26/2025",
    "competitionYear": "-1"
  },
  {
    "event": "50 BK LCM",
    "swimTime": "40.36",
    "age": "10",
    "points": "594",
    "timeStandard": "AA",
    "meet": "2025 NT TFA Quacken A & Above",
    "lsc": "NT",
    "team": "Lakeside Aquatic Club",
    "swimDate": "07/26/2025",
    "competitionYear": "-1"
  },
  {
    "event": "50 BK LCM",
    "swimTime": "40.63",
    "age": "10",
    "points": "581",
    "timeStandard": "AA",
    "meet": "2025 NT North Texas Long Course Age Group Championship",
    "lsc": "NT",
    "team": "Lakeside Aquatic Club",
    "swimDate": "06/29/2025",
    "competitionYear": "-1"
  },
  {
    "event": "50 BK LCM",
    "swimTime": "41.13",
    "age": "10",
    "points": "557",
    "timeStandard": "A",
    "meet": "2025 NT TFA July Time Trial",
    "lsc": "NT",
    "team": "Lakeside Aquatic Club",
    "swimDate": "07/09/2025",
    "competitionYear": "-1"
  },
  {
    "event": "50 BK LCM",
    "swimTime": "41.16r",
    "age": "10",
    "points": "555",
    "timeStandard": "A",
    "meet": "2025 NT North Texas Long Course Age Group Championship",
    "lsc": "NT",
    "team": "Lakeside Aquatic Club",
    "swimDate": "06/27/2025",
    "competitionYear": "-1"
  },
  {
    "event": "50 BK LCM",
    "swimTime": "41.26",
    "age": "10",
    "points": "550",
    "timeStandard": "A",
    "meet": "2025 NT North Texas Long Course Age Group Championship",
    "lsc": "NT",
    "team": "Lakeside Aquatic Club",
    "swimDate": "06/29/2025",
    "competitionYear": "-1"
  },
  {
    "event": "50 BK LCM",
    "swimTime": "42.10",
    "age": "10",
    "points": "510",
    "timeStandard": "A",
    "meet": "2025 NT LAC Hiroto Kobukai Memorial Invite",
    "lsc": "NT",
    "team": "Lakeside Aquatic Club",
    "swimDate": "05/18/2025",
    "competitionYear": "-1"
  },
  {
    "event": "50 BK LCM",
    "swimTime": "42.53",
    "age": "10",
    "points": "490",
    "timeStandard": "A",
    "meet": "2025 NT MARS Bill Nixon Memorial Invite",
    "lsc": "NT",
    "team": "Lakeside Aquatic Club",
    "swimDate": "06/07/2025",
    "competitionYear": "-1"
  },
  {
    "event": "50 BK LCM",
    "swimTime": "43.28",
    "age": "10",
    "points": "456",
    "timeStandard": "BB",
    "meet": "2025 NT STAR April Long Course No Bulkhead, No Problem Open",
    "lsc": "NT",
    "team": "Lakeside Aquatic Club",
    "swimDate": "04/05/2025",
    "competitionYear": "-1"
  },
  {
    "event": "50 BK LCM",
    "swimTime": "43.64",
    "age": "10",
    "points": "440",
    "timeStandard": "BB",
    "meet": "2025 NT STAR April A/BB East Division Meet",
    "lsc": "NT",
    "team": "Lakeside Aquatic Club",
    "swimDate": "04/26/2025",
    "competitionYear": "-1"
  },
  {
    "event": "50 BK LCM",
    "swimTime": "47.46",
    "age": "9",
    "points": "399",
    "timeStandard": "2020-2024 BB",
    "meet": "2024 NT LAC Fun in the Sun",
    "lsc": "NT",
    "team": "Lakeside Aquatic Club",
    "swimDate": "07/06/2024",
    "competitionYear": "-1"
  },
  {
    "event": "100 BK LCM",
    "swimTime": "1:27.07",
    "age": "10",
    "points": "606",
    "timeStandard": "AA",
    "meet": "2025 NT North Texas Long Course Age Group Championship",
    "lsc": "NT",
    "team": "Lakeside Aquatic Club",
    "swimDate": "06/27/2025",
    "competitionYear": "-1"
  },
  {
    "event": "100 BK LCM",
    "swimTime": "1:27.78",
    "age": "10",
    "points": "590",
    "timeStandard": "AA",
    "meet": "2025 NT TFA Quacken A & Above",
    "lsc": "NT",
    "team": "Lakeside Aquatic Club",
    "swimDate": "07/27/2025",
    "competitionYear": "-1"
  },
  {
    "event": "100 BK LCM",
    "swimTime": "1:28.22",
    "age": "10",
    "points": "580",
    "timeStandard": "A",
    "meet": "2025 NT North Texas Long Course Age Group Championship",
    "lsc": "NT",
    "team": "Lakeside Aquatic Club",
    "swimDate": "06/27/2025",
    "competitionYear": "-1"
  },
  {
    "event": "100 BK LCM",
    "swimTime": "1:30.65",
    "age": "10",
    "points": "525",
    "timeStandard": "A",
    "meet": "2025 NT LAC Hiroto Kobukai Memorial Invite",
    "lsc": "NT",
    "team": "Lakeside Aquatic Club",
    "swimDate": "05/17/2025",
    "competitionYear": "-1"
  },
  {
    "event": "100 BK LCM",
    "swimTime": "1:32.81",
    "age": "10",
    "points": "479",
    "timeStandard": "BB",
    "meet": "2025 NT STAR April A/BB East Division Meet",
    "lsc": "NT",
    "team": "Lakeside Aquatic Club",
    "swimDate": "04/27/2025",
    "competitionYear": "-1"
  },
  {
    "event": "100 BK LCM",
    "swimTime": "1:35.65",
    "age": "10",
    "points": "420",
    "timeStandard": "BB",
    "meet": "2025 NT STAR April Long Course No Bulkhead, No Problem Open",
    "lsc": "NT",
    "team": "Lakeside Aquatic Club",
    "swimDate": "04/06/2025",
    "competitionYear": "-1"
  },
  {
    "event": "100 BK LCM",
    "swimTime": "1:38.97",
    "age": "9",
    "points": "478",
    "timeStandard": "2020-2024 BB",
    "meet": "2024 NT LAC Fun in the Sun",
    "lsc": "NT",
    "team": "Lakeside Aquatic Club",
    "swimDate": "07/07/2024",
    "competitionYear": "-1"
  },
  {
    "event": "50 BR LCM",
    "swimTime": "49.79",
    "age": "10",
    "points": "413",
    "timeStandard": "BB",
    "meet": "2025 NT TFA Quacken A & Above",
    "lsc": "NT",
    "team": "Lakeside Aquatic Club",
    "swimDate": "07/27/2025",
    "competitionYear": "-1"
  },
  {
    "event": "50 BR LCM",
    "swimTime": "51.56",
    "age": "10",
    "points": "347",
    "timeStandard": "BB",
    "meet": "2025 NT STAR April Long Course No Bulkhead, No Problem Open",
    "lsc": "NT",
    "team": "Lakeside Aquatic Club",
    "swimDate": "04/06/2025",
    "competitionYear": "-1"
  },
  {
    "event": "50 BR LCM",
    "swimTime": "52.96",
    "age": "10",
    "points": "297",
    "timeStandard": "BB",
    "meet": "2025 NT LAC Hiroto Kobukai Memorial Invite",
    "lsc": "NT",
    "team": "Lakeside Aquatic Club",
    "swimDate": "05/17/2025",
    "competitionYear": "-1"
  },
  {
    "event": "50 BR LCM",
    "swimTime": "53.13",
    "age": "9",
    "points": "439",
    "timeStandard": "2020-2024 BB",
    "meet": "2024 NT LAC Fun in the Sun",
    "lsc": "NT",
    "team": "Lakeside Aquatic Club",
    "swimDate": "07/07/2024",
    "competitionYear": "-1"
  },
  {
    "event": "50 BR LCM",
    "swimTime": "53.42",
    "age": "10",
    "points": "281",
    "timeStandard": "BB",
    "meet": "2025 NT STAR April A/BB East Division Meet",
    "lsc": "NT",
    "team": "Lakeside Aquatic Club",
    "swimDate": "04/27/2025",
    "competitionYear": "-1"
  },
  {
    "event": "100 BR LCM",
    "swimTime": "1:49.29",
    "age": "10",
    "points": "419",
    "timeStandard": "BB",
    "meet": "2025 NT North Texas Long Course Age Group Championship",
    "lsc": "NT",
    "team": "Lakeside Aquatic Club",
    "swimDate": "06/29/2025",
    "competitionYear": "-1"
  },
  {
    "event": "100 BR LCM",
    "swimTime": "1:55.09",
    "age": "10",
    "points": "322",
    "timeStandard": "BB",
    "meet": "2025 NT LAC Hiroto Kobukai Memorial Invite",
    "lsc": "NT",
    "team": "Lakeside Aquatic Club",
    "swimDate": "05/18/2025",
    "competitionYear": "-1"
  },
  {
    "event": "100 BR LCM",
    "swimTime": "1:55.29",
    "age": "9",
    "points": "456",
    "timeStandard": "2020-2024 BB",
    "meet": "2024 NT LAC Fun in the Sun",
    "lsc": "NT",
    "team": "Lakeside Aquatic Club",
    "swimDate": "07/06/2024",
    "competitionYear": "-1"
  },
  {
    "event": "100 BR LCM",
    "swimTime": "1:56.05",
    "age": "10",
    "points": "307",
    "timeStandard": "BB",
    "meet": "2025 NT STAR April A/BB East Division Meet",
    "lsc": "NT",
    "team": "Lakeside Aquatic Club",
    "swimDate": "04/26/2025",
    "competitionYear": "-1"
  },
  {
    "event": "50 FL LCM",
    "swimTime": "42.13",
    "age": "10",
    "points": "364",
    "timeStandard": "BB",
    "meet": "2025 NT TFA Quacken A & Above",
    "lsc": "NT",
    "team": "Lakeside Aquatic Club",
    "swimDate": "07/27/2025",
    "competitionYear": "-1"
  },
  {
    "event": "50 FL LCM",
    "swimTime": "46.81",
    "age": "10",
    "points": "173",
    "timeStandard": "B",
    "meet": "2025 NT STAR April Long Course No Bulkhead, No Problem Open",
    "lsc": "NT",
    "team": "Lakeside Aquatic Club",
    "swimDate": "04/06/2025",
    "competitionYear": "-1"
  },
  {
    "event": "100 FL LCM",
    "swimTime": "1:41.97",
    "age": "10",
    "points": "275",
    "timeStandard": "BB",
    "meet": "2025 NT MARS Bill Nixon Memorial Invite",
    "lsc": "NT",
    "team": "Lakeside Aquatic Club",
    "swimDate": "06/07/2025",
    "competitionYear": "-1"
  },
  {
    "event": "200 IM LCM",
    "swimTime": "3:23.15",
    "age": "10",
    "points": "390",
    "timeStandard": "BB",
    "meet": "2025 NT LAC Hiroto Kobukai Memorial Invite",
    "lsc": "NT",
    "team": "Lakeside Aquatic Club",
    "swimDate": "05/17/2025",
    "competitionYear": "-1"
  },
  {
    "event": "200 IM LCM",
    "swimTime": "3:27.15",
    "age": "10",
    "points": "352",
    "timeStandard": "BB",
    "meet": "2025 NT STAR April A/BB East Division Meet",
    "lsc": "NT",
    "team": "Lakeside Aquatic Club",
    "swimDate": "04/26/2025",
    "competitionYear": "-1"
  },
  {
    "event": "50 FR SCY",
    "swimTime": "32.24",
    "age": "10",
    "points": "495",
    "timeStandard": "BB",
    "meet": "2025 NT LAC Splashing Pumpkins",
    "lsc": "NT",
    "team": "Lakeside Aquatic Club",
    "swimDate": "10/04/2025",
    "competitionYear": "2026"
  },
  {
    "event": "100 FR SCY",
    "swimTime": "1:13.25",
    "age": "10",
    "points": "382",
    "timeStandard": "BB",
    "meet": "2025 NT LAC Splashing Pumpkins",
    "lsc": "NT",
    "team": "Lakeside Aquatic Club",
    "swimDate": "10/05/2025",
    "competitionYear": "2026"
  },
  {
    "event": "200 FR SCY",
    "swimTime": "2:32.37",
    "age": "10",
    "points": "437",
    "timeStandard": "BB",
    "meet": "2025 NT LAC Splashing Pumpkins",
    "lsc": "NT",
    "team": "Lakeside Aquatic Club",
    "swimDate": "10/04/2025",
    "competitionYear": "2026"
  },
  {
    "event": "50 BK SCY",
    "swimTime": "35.96",
    "age": "10",
    "points": "552",
    "timeStandard": "A",
    "meet": "2025 NT LAC Splashing Pumpkins",
    "lsc": "NT",
    "team": "Lakeside Aquatic Club",
    "swimDate": "10/04/2025",
    "competitionYear": "2026"
  },
  {
    "event": "100 BK SCY",
    "swimTime": "1:17.21",
    "age": "10",
    "points": "550",
    "timeStandard": "A",
    "meet": "2025 NT LAC Splashing Pumpkins",
    "lsc": "NT",
    "team": "Lakeside Aquatic Club",
    "swimDate": "10/05/2025",
    "competitionYear": "2026"
  },
  {
    "event": "100 IM SCY",
    "swimTime": "1:22.34",
    "age": "10",
    "points": "406",
    "timeStandard": "BB",
    "meet": "2025 NT LAC Splashing Pumpkins",
    "lsc": "NT",
    "team": "Lakeside Aquatic Club",
    "swimDate": "10/05/2025",
    "competitionYear": "2026"
  },
  {
    "event": "50 FR SCY",
    "swimTime": "34.54",
    "age": "10",
    "points": "368",
    "timeStandard": "BB",
    "meet": "2025 NT LAC Heart Racer",
    "lsc": "NT",
    "team": "Lakeside Aquatic Club",
    "swimDate": "02/16/2025",
    "competitionYear": "2025"
  },
  {
    "event": "50 FR SCY",
    "swimTime": "35.22",
    "age": "9",
    "points": "446",
    "timeStandard": "B",
    "meet": "2024 NT LAC Splashing Pumpkins",
    "lsc": "NT",
    "team": "Lakeside Aquatic Club",
    "swimDate": "10/06/2024",
    "competitionYear": "2025"
  },
  {
    "event": "50 FR SCY",
    "swimTime": "35.82",
    "age": "9",
    "points": "415",
    "timeStandard": "B",
    "meet": "2024 NT LAC A-Maize-ing Autumn Meet",
    "lsc": "NT",
    "team": "Lakeside Aquatic Club",
    "swimDate": "11/10/2024",
    "competitionYear": "2025"
  },
  {
    "event": "100 FR SCY",
    "swimTime": "1:15.88",
    "age": "10",
    "points": "315",
    "timeStandard": "BB",
    "meet": "2025 NT STAR We Love Flip Turns Meet",
    "lsc": "NT",
    "team": "Lakeside Aquatic Club",
    "swimDate": "06/15/2025",
    "competitionYear": "2025"
  },
  {
    "event": "100 FR SCY",
    "swimTime": "1:20.47",
    "age": "10",
    "points": "209",
    "timeStandard": "B",
    "meet": "2024 NT LAC Jingle Bell",
    "lsc": "NT",
    "team": "Lakeside Aquatic Club",
    "swimDate": "12/15/2024",
    "competitionYear": "2025"
  },
  {
    "event": "500 FR SCY",
    "swimTime": "7:21.91",
    "age": "10",
    "points": "276",
    "timeStandard": "BB",
    "meet": "2025 NT STAR We Love Flip Turns Meet",
    "lsc": "NT",
    "team": "Lakeside Aquatic Club",
    "swimDate": "06/15/2025",
    "competitionYear": "2025"
  },
  {
    "event": "50 BK SCY",
    "swimTime": "39.82",
    "age": "10",
    "points": "353",
    "timeStandard": "BB",
    "meet": "2024 NT LAC Jingle Bell",
    "lsc": "NT",
    "team": "Lakeside Aquatic Club",
    "swimDate": "12/15/2024",
    "competitionYear": "2025"
  },
  {
    "event": "50 BK SCY",
    "swimTime": "41.06",
    "age": "9",
    "points": "421",
    "timeStandard": "BB",
    "meet": "2024 NT LAC Splashing Pumpkins",
    "lsc": "NT",
    "team": "Lakeside Aquatic Club",
    "swimDate": "10/05/2024",
    "competitionYear": "2025"
  },
  {
    "event": "100 BK SCY",
    "swimTime": "1:21.29",
    "age": "10",
    "points": "448",
    "timeStandard": "BB",
    "meet": "2025 NT LAC Heart Racer",
    "lsc": "NT",
    "team": "Lakeside Aquatic Club",
    "swimDate": "02/16/2025",
    "competitionYear": "2025"
  },
  {
    "event": "100 BK SCY",
    "swimTime": "1:23.32",
    "age": "10",
    "points": "400",
    "timeStandard": "BB",
    "meet": "2024 NT LAC Jingle Bell",
    "lsc": "NT",
    "team": "Lakeside Aquatic Club",
    "swimDate": "12/14/2024",
    "competitionYear": "2025"
  },
  {
    "event": "50 BR SCY",
    "swimTime": "46.67",
    "age": "9",
    "points": "403",
    "timeStandard": "BB",
    "meet": "2024 NT LAC Splashing Pumpkins",
    "lsc": "NT",
    "team": "Lakeside Aquatic Club",
    "swimDate": "10/05/2024",
    "competitionYear": "2025"
  },
  {
    "event": "50 BR SCY",
    "swimTime": "47.02",
    "age": "10",
    "points": "247",
    "timeStandard": "BB",
    "meet": "2024 NT LAC Jingle Bell",
    "lsc": "NT",
    "team": "Lakeside Aquatic Club",
    "swimDate": "12/14/2024",
    "competitionYear": "2025"
  },
  {
    "event": "50 BR SCY",
    "swimTime": "47.94",
    "age": "10",
    "points": "213",
    "timeStandard": "B",
    "meet": "2025 NT STAR We Love Flip Turns Meet",
    "lsc": "NT",
    "team": "Lakeside Aquatic Club",
    "swimDate": "06/15/2025",
    "competitionYear": "2025"
  },
  {
    "event": "100 BR SCY",
    "swimTime": "1:40.33",
    "age": "10",
    "points": "289",
    "timeStandard": "BB",
    "meet": "2024 NT LAC Jingle Bell",
    "lsc": "NT",
    "team": "Lakeside Aquatic Club",
    "swimDate": "12/15/2024",
    "competitionYear": "2025"
  },
  {
    "event": "100 BR SCY",
    "swimTime": "1:40.47",
    "age": "10",
    "points": "286",
    "timeStandard": "BB",
    "meet": "2025 NT LAC Heart Racer",
    "lsc": "NT",
    "team": "Lakeside Aquatic Club",
    "swimDate": "02/16/2025",
    "competitionYear": "2025"
  },
  {
    "event": "50 FL SCY",
    "swimTime": "41.71",
    "age": "9",
    "points": "282",
    "timeStandard": "B",
    "meet": "2024 NT LAC A-Maize-ing Autumn Meet",
    "lsc": "NT",
    "team": "Lakeside Aquatic Club",
    "swimDate": "11/10/2024",
    "competitionYear": "2025"
  },
  {
    "event": "50 FL SCY",
    "swimTime": "42.33",
    "age": "10",
    "points": "127",
    "timeStandard": "B",
    "meet": "2025 NT STAR We Love Flip Turns Meet",
    "lsc": "NT",
    "team": "Lakeside Aquatic Club",
    "swimDate": "06/15/2025",
    "competitionYear": "2025"
  },
  {
    "event": "50 FL SCY",
    "swimTime": "42.57",
    "age": "9",
    "points": "245",
    "timeStandard": "B",
    "meet": "2024 NT LAC Splashing Pumpkins",
    "lsc": "NT",
    "team": "Lakeside Aquatic Club",
    "swimDate": "10/06/2024",
    "competitionYear": "2025"
  },
  {
    "event": "100 FL SCY",
    "swimTime": "1:34.29",
    "age": "10",
    "points": "182",
    "timeStandard": "BB",
    "meet": "2024 NT LAC Jingle Bell",
    "lsc": "NT",
    "team": "Lakeside Aquatic Club",
    "swimDate": "12/14/2024",
    "competitionYear": "2025"
  },
  {
    "event": "100 IM SCY",
    "swimTime": "1:27.94",
    "age": "10",
    "points": "276",
    "timeStandard": "BB",
    "meet": "2025 NT STAR We Love Flip Turns Meet",
    "lsc": "NT",
    "team": "Lakeside Aquatic Club",
    "swimDate": "06/15/2025",
    "competitionYear": "2025"
  },
  {
    "event": "100 IM SCY",
    "swimTime": "1:28.41",
    "age": "9",
    "points": "403",
    "timeStandard": "BB",
    "meet": "2024 NT LAC A-Maize-ing Autumn Meet",
    "lsc": "NT",
    "team": "Lakeside Aquatic Club",
    "swimDate": "11/10/2024",
    "competitionYear": "2025"
  },
  {
    "event": "100 IM SCY",
    "swimTime": "1:30.00",
    "age": "9",
    "points": "367",
    "timeStandard": "B",
    "meet": "2024 NT LAC Splashing Pumpkins",
    "lsc": "NT",
    "team": "Lakeside Aquatic Club",
    "swimDate": "10/06/2024",
    "competitionYear": "2025"
  },
  {
    "event": "200 IM SCY",
    "swimTime": "3:04.16",
    "age": "10",
    "points": "327",
    "timeStandard": "BB",
    "meet": "2025 NT LAC Heart Racer",
    "lsc": "NT",
    "team": "Lakeside Aquatic Club",
    "swimDate": "02/14/2025",
    "competitionYear": "2025"
  },
  {
    "event": "50 FR LCM",
    "swimTime": "35.06",
    "age": "10",
    "points": "597",
    "timeStandard": "A",
    "meet": "2025 NT Texas Age Group Long Course Time Trials",
    "lsc": "NT",
    "team": "Lakeside Aquatic Club",
    "swimDate": "07/18/2025",
    "competitionYear": "2025"
  },
  {
    "event": "50 FR LCM",
    "swimTime": "36.55",
    "age": "10",
    "points": "521",
    "timeStandard": "BB",
    "meet": "2025 NT North Texas Long Course Age Group Championship",
    "lsc": "NT",
    "team": "Lakeside Aquatic Club",
    "swimDate": "06/27/2025",
    "competitionYear": "2025"
  },
  {
    "event": "50 FR LCM",
    "swimTime": "37.14",
    "age": "10",
    "points": "492",
    "timeStandard": "BB",
    "meet": "2025 NT STAR April A/BB East Division Meet",
    "lsc": "NT",
    "team": "Lakeside Aquatic Club",
    "swimDate": "04/26/2025",
    "competitionYear": "2025"
  },
  {
    "event": "50 FR LCM",
    "swimTime": "37.70",
    "age": "10",
    "points": "464",
    "timeStandard": "BB",
    "meet": "2025 NT STAR April Long Course No Bulkhead, No Problem Open",
    "lsc": "NT",
    "team": "Lakeside Aquatic Club",
    "swimDate": "04/05/2025",
    "competitionYear": "2025"
  },
  {
    "event": "50 FR LCM",
    "swimTime": "37.88",
    "age": "10",
    "points": "455",
    "timeStandard": "BB",
    "meet": "2025 NT LAC Hiroto Kobukai Memorial Invite",
    "lsc": "NT",
    "team": "Lakeside Aquatic Club",
    "swimDate": "05/18/2025",
    "competitionYear": "2025"
  },
  {
    "event": "100 FR LCM",
    "swimTime": "1:17.14r",
    "age": "10",
    "points": "547",
    "timeStandard": "A",
    "meet": "2025 NT Texas Age Group Long Course Championships",
    "lsc": "NT",
    "team": "Lakeside Aquatic Club",
    "swimDate": "07/18/2025",
    "competitionYear": "2025"
  },
  {
    "event": "100 FR LCM",
    "swimTime": "1:17.41",
    "age": "10",
    "points": "540",
    "timeStandard": "A",
    "meet": "2025 NT North Texas Long Course Age Group Championship",
    "lsc": "NT",
    "team": "Lakeside Aquatic Club",
    "swimDate": "06/29/2025",
    "competitionYear": "2025"
  },
  {
    "event": "100 FR LCM",
    "swimTime": "1:17.92",
    "age": "10",
    "points": "527",
    "timeStandard": "A",
    "meet": "2025 NT North Texas Long Course Age Group Championship",
    "lsc": "NT",
    "team": "Lakeside Aquatic Club",
    "swimDate": "06/29/2025",
    "competitionYear": "2025"
  },
  {
    "event": "100 FR LCM",
    "swimTime": "1:22.01",
    "age": "10",
    "points": "425",
    "timeStandard": "BB",
    "meet": "2025 NT STAR April A/BB East Division Meet",
    "lsc": "NT",
    "team": "Lakeside Aquatic Club",
    "swimDate": "04/27/2025",
    "competitionYear": "2025"
  },
  {
    "event": "200 FR LCM",
    "swimTime": "2:48.33",
    "age": "10",
    "points": "504",
    "timeStandard": "A",
    "meet": "2025 NT TFA Quacken A & Above",
    "lsc": "NT",
    "team": "Lakeside Aquatic Club",
    "swimDate": "07/26/2025",
    "competitionYear": "2025"
  },
  {
    "event": "400 FR LCM",
    "swimTime": "6:07.85",
    "age": "10",
    "points": "453",
    "timeStandard": "BB",
    "meet": "2025 NT TFA Quacken A & Above",
    "lsc": "NT",
    "team": "Lakeside Aquatic Club",
    "swimDate": "07/26/2025",
    "competitionYear": "2025"
  },
  {
    "event": "50 BK LCM",
    "swimTime": "40.36",
    "age": "10",
    "points": "594",
    "timeStandard": "AA",
    "meet": "2025 NT TFA Quacken A & Above",
    "lsc": "NT",
    "team": "Lakeside Aquatic Club",
    "swimDate": "07/26/2025",
    "competitionYear": "2025"
  },
  {
    "event": "50 BK LCM",
    "swimTime": "40.63",
    "age": "10",
    "points": "581",
    "timeStandard": "AA",
    "meet": "2025 NT North Texas Long Course Age Group Championship",
    "lsc": "NT",
    "team": "Lakeside Aquatic Club",
    "swimDate": "06/29/2025",
    "competitionYear": "2025"
  },
  {
    "event": "50 BK LCM",
    "swimTime": "41.13",
    "age": "10",
    "points": "557",
    "timeStandard": "A",
    "meet": "2025 NT TFA July Time Trial",
    "lsc": "NT",
    "team": "Lakeside Aquatic Club",
    "swimDate": "07/09/2025",
    "competitionYear": "2025"
  },
  {
    "event": "50 BK LCM",
    "swimTime": "41.16r",
    "age": "10",
    "points": "555",
    "timeStandard": "A",
    "meet": "2025 NT North Texas Long Course Age Group Championship",
    "lsc": "NT",
    "team": "Lakeside Aquatic Club",
    "swimDate": "06/27/2025",
    "competitionYear": "2025"
  },
  {
    "event": "50 BK LCM",
    "swimTime": "41.26",
    "age": "10",
    "points": "550",
    "timeStandard": "A",
    "meet": "2025 NT North Texas Long Course Age Group Championship",
    "lsc": "NT",
    "team": "Lakeside Aquatic Club",
    "swimDate": "06/29/2025",
    "competitionYear": "2025"
  },
  {
    "event": "50 BK LCM",
    "swimTime": "42.10",
    "age": "10",
    "points": "510",
    "timeStandard": "A",
    "meet": "2025 NT LAC Hiroto Kobukai Memorial Invite",
    "lsc": "NT",
    "team": "Lakeside Aquatic Club",
    "swimDate": "05/18/2025",
    "competitionYear": "2025"
  },
  {
    "event": "50 BK LCM",
    "swimTime": "42.53",
    "age": "10",
    "points": "490",
    "timeStandard": "A",
    "meet": "2025 NT MARS Bill Nixon Memorial Invite",
    "lsc": "NT",
    "team": "Lakeside Aquatic Club",
    "swimDate": "06/07/2025",
    "competitionYear": "2025"
  },
  {
    "event": "50 BK LCM",
    "swimTime": "43.28",
    "age": "10",
    "points": "456",
    "timeStandard": "BB",
    "meet": "2025 NT STAR April Long Course No Bulkhead, No Problem Open",
    "lsc": "NT",
    "team": "Lakeside Aquatic Club",
    "swimDate": "04/05/2025",
    "competitionYear": "2025"
  },
  {
    "event": "50 BK LCM",
    "swimTime": "43.64",
    "age": "10",
    "points": "440",
    "timeStandard": "BB",
    "meet": "2025 NT STAR April A/BB East Division Meet",
    "lsc": "NT",
    "team": "Lakeside Aquatic Club",
    "swimDate": "04/26/2025",
    "competitionYear": "2025"
  },
  {
    "event": "100 BK LCM",
    "swimTime": "1:27.07",
    "age": "10",
    "points": "606",
    "timeStandard": "AA",
    "meet": "2025 NT North Texas Long Course Age Group Championship",
    "lsc": "NT",
    "team": "Lakeside Aquatic Club",
    "swimDate": "06/27/2025",
    "competitionYear": "2025"
  },
  {
    "event": "100 BK LCM",
    "swimTime": "1:27.78",
    "age": "10",
    "points": "590",
    "timeStandard": "AA",
    "meet": "2025 NT TFA Quacken A & Above",
    "lsc": "NT",
    "team": "Lakeside Aquatic Club",
    "swimDate": "07/27/2025",
    "competitionYear": "2025"
  },
  {
    "event": "100 BK LCM",
    "swimTime": "1:28.22",
    "age": "10",
    "points": "580",
    "timeStandard": "A",
    "meet": "2025 NT North Texas Long Course Age Group Championship",
    "lsc": "NT",
    "team": "Lakeside Aquatic Club",
    "swimDate": "06/27/2025",
    "competitionYear": "2025"
  },
  {
    "event": "100 BK LCM",
    "swimTime": "1:30.65",
    "age": "10",
    "points": "525",
    "timeStandard": "A",
    "meet": "2025 NT LAC Hiroto Kobukai Memorial Invite",
    "lsc": "NT",
    "team": "Lakeside Aquatic Club",
    "swimDate": "05/17/2025",
    "competitionYear": "2025"
  },
  {
    "event": "100 BK LCM",
    "swimTime": "1:32.81",
    "age": "10",
    "points": "479",
    "timeStandard": "BB",
    "meet": "2025 NT STAR April A/BB East Division Meet",
    "lsc": "NT",
    "team": "Lakeside Aquatic Club",
    "swimDate": "04/27/2025",
    "competitionYear": "2025"
  },
  {
    "event": "100 BK LCM",
    "swimTime": "1:35.65",
    "age": "10",
    "points": "420",
    "timeStandard": "BB",
    "meet": "2025 NT STAR April Long Course No Bulkhead, No Problem Open",
    "lsc": "NT",
    "team": "Lakeside Aquatic Club",
    "swimDate": "04/06/2025",
    "competitionYear": "2025"
  },
  {
    "event": "50 BR LCM",
    "swimTime": "49.79",
    "age": "10",
    "points": "413",
    "timeStandard": "BB",
    "meet": "2025 NT TFA Quacken A & Above",
    "lsc": "NT",
    "team": "Lakeside Aquatic Club",
    "swimDate": "07/27/2025",
    "competitionYear": "2025"
  },
  {
    "event": "50 BR LCM",
    "swimTime": "51.56",
    "age": "10",
    "points": "347",
    "timeStandard": "BB",
    "meet": "2025 NT STAR April Long Course No Bulkhead, No Problem Open",
    "lsc": "NT",
    "team": "Lakeside Aquatic Club",
    "swimDate": "04/06/2025",
    "competitionYear": "2025"
  },
  {
    "event": "50 BR LCM",
    "swimTime": "52.96",
    "age": "10",
    "points": "297",
    "timeStandard": "BB",
    "meet": "2025 NT LAC Hiroto Kobukai Memorial Invite",
    "lsc": "NT",
    "team": "Lakeside Aquatic Club",
    "swimDate": "05/17/2025",
    "competitionYear": "2025"
  },
  {
    "event": "50 BR LCM",
    "swimTime": "53.42",
    "age": "10",
    "points": "281",
    "timeStandard": "BB",
    "meet": "2025 NT STAR April A/BB East Division Meet",
    "lsc": "NT",
    "team": "Lakeside Aquatic Club",
    "swimDate": "04/27/2025",
    "competitionYear": "2025"
  },
  {
    "event": "100 BR LCM",
    "swimTime": "1:49.29",
    "age": "10",
    "points": "419",
    "timeStandard": "BB",
    "meet": "2025 NT North Texas Long Course Age Group Championship",
    "lsc": "NT",
    "team": "Lakeside Aquatic Club",
    "swimDate": "06/29/2025",
    "competitionYear": "2025"
  },
  {
    "event": "100 BR LCM",
    "swimTime": "1:55.09",
    "age": "10",
    "points": "322",
    "timeStandard": "BB",
    "meet": "2025 NT LAC Hiroto Kobukai Memorial Invite",
    "lsc": "NT",
    "team": "Lakeside Aquatic Club",
    "swimDate": "05/18/2025",
    "competitionYear": "2025"
  },
  {
    "event": "100 BR LCM",
    "swimTime": "1:56.05",
    "age": "10",
    "points": "307",
    "timeStandard": "BB",
    "meet": "2025 NT STAR April A/BB East Division Meet",
    "lsc": "NT",
    "team": "Lakeside Aquatic Club",
    "swimDate": "04/26/2025",
    "competitionYear": "2025"
  },
  {
    "event": "50 FL LCM",
    "swimTime": "42.13",
    "age": "10",
    "points": "364",
    "timeStandard": "BB",
    "meet": "2025 NT TFA Quacken A & Above",
    "lsc": "NT",
    "team": "Lakeside Aquatic Club",
    "swimDate": "07/27/2025",
    "competitionYear": "2025"
  },
  {
    "event": "50 FL LCM",
    "swimTime": "46.81",
    "age": "10",
    "points": "173",
    "timeStandard": "B",
    "meet": "2025 NT STAR April Long Course No Bulkhead, No Problem Open",
    "lsc": "NT",
    "team": "Lakeside Aquatic Club",
    "swimDate": "04/06/2025",
    "competitionYear": "2025"
  },
  {
    "event": "100 FL LCM",
    "swimTime": "1:41.97",
    "age": "10",
    "points": "275",
    "timeStandard": "BB",
    "meet": "2025 NT MARS Bill Nixon Memorial Invite",
    "lsc": "NT",
    "team": "Lakeside Aquatic Club",
    "swimDate": "06/07/2025",
    "competitionYear": "2025"
  },
  {
    "event": "200 IM LCM",
    "swimTime": "3:23.15",
    "age": "10",
    "points": "390",
    "timeStandard": "BB",
    "meet": "2025 NT LAC Hiroto Kobukai Memorial Invite",
    "lsc": "NT",
    "team": "Lakeside Aquatic Club",
    "swimDate": "05/17/2025",
    "competitionYear": "2025"
  },
  {
    "event": "200 IM LCM",
    "swimTime": "3:27.15",
    "age": "10",
    "points": "352",
    "timeStandard": "BB",
    "meet": "2025 NT STAR April A/BB East Division Meet",
    "lsc": "NT",
    "team": "Lakeside Aquatic Club",
    "swimDate": "04/26/2025",
    "competitionYear": "2025"
  },
  {
    "event": "50 FR SCY",
    "swimTime": "37.31",
    "age": "9",
    "points": "340",
    "timeStandard": "2020-2024 B",
    "meet": "2024 NT LAC Season Opener",
    "lsc": "NT",
    "team": "Lakeside Aquatic Club",
    "swimDate": "04/13/2024",
    "competitionYear": "2024"
  },
  {
    "event": "50 FR SCY",
    "swimTime": "37.92",
    "age": "9",
    "points": "310",
    "timeStandard": "2020-2024 B",
    "meet": "2024 NT LAC May Madness Meet",
    "lsc": "NT",
    "team": "Lakeside Aquatic Club",
    "swimDate": "05/05/2024",
    "competitionYear": "2024"
  },
  {
    "event": "50 FR SCY",
    "swimTime": "38.34",
    "age": "8",
    "points": "290",
    "timeStandard": "Slower than B",
    "meet": "2023 NT LAC Jingle Bell Meet",
    "lsc": "NT",
    "team": "Lakeside Aquatic Club",
    "swimDate": "12/09/2023",
    "competitionYear": "2024"
  },
  {
    "event": "50 FR SCY",
    "swimTime": "38.39",
    "age": "8",
    "points": "288",
    "timeStandard": "Slower than B",
    "meet": "2023 NT LAC Spooky Splash Intrasquad Meet",
    "lsc": "NT",
    "team": "Lakeside Aquatic Club",
    "swimDate": "10/22/2023",
    "competitionYear": "2024"
  },
  {
    "event": "100 FR SCY",
    "swimTime": "1:24.16",
    "age": "8",
    "points": "256",
    "timeStandard": "2020-2024 B",
    "meet": "2023 NT LAC Spooky Splash Intrasquad Meet",
    "lsc": "NT",
    "team": "Lakeside Aquatic Club",
    "swimDate": "10/22/2023",
    "competitionYear": "2024"
  },
  {
    "event": "100 FR SCY",
    "swimTime": "1:25.03",
    "age": "9",
    "points": "237",
    "timeStandard": "2020-2024 B",
    "meet": "2024 NT LAC Season Opener",
    "lsc": "NT",
    "team": "Lakeside Aquatic Club",
    "swimDate": "04/14/2024",
    "competitionYear": "2024"
  },
  {
    "event": "100 FR SCY",
    "swimTime": "1:25.81",
    "age": "9",
    "points": "221",
    "timeStandard": "2020-2024 B",
    "meet": "2024 NT LAC Ice Breaker",
    "lsc": "NT",
    "team": "Lakeside Aquatic Club",
    "swimDate": "01/06/2024",
    "competitionYear": "2024"
  },
  {
    "event": "200 FR SCY",
    "swimTime": "3:05.02",
    "age": "8",
    "points": "204",
    "timeStandard": "2020-2024 B",
    "meet": "2023 NT LAC Jingle Bell Meet",
    "lsc": "NT",
    "team": "Lakeside Aquatic Club",
    "swimDate": "12/09/2023",
    "competitionYear": "2024"
  },
  {
    "event": "50 BK SCY",
    "swimTime": "42.28",
    "age": "9",
    "points": "365",
    "timeStandard": "2020-2024 BB",
    "meet": "2024 NT LAC Ice Breaker",
    "lsc": "NT",
    "team": "Lakeside Aquatic Club",
    "swimDate": "01/06/2024",
    "competitionYear": "2024"
  },
  {
    "event": "50 BK SCY",
    "swimTime": "42.30",
    "age": "9",
    "points": "364",
    "timeStandard": "2020-2024 B",
    "meet": "2024 NT LAC Season Opener",
    "lsc": "NT",
    "team": "Lakeside Aquatic Club",
    "swimDate": "04/14/2024",
    "competitionYear": "2024"
  },
  {
    "event": "50 BK SCY",
    "swimTime": "42.95",
    "age": "8",
    "points": "335",
    "timeStandard": "2020-2024 B",
    "meet": "2023 NT LAC Jingle Bell Meet",
    "lsc": "NT",
    "team": "Lakeside Aquatic Club",
    "swimDate": "12/10/2023",
    "competitionYear": "2024"
  },
  {
    "event": "50 BK SCY",
    "swimTime": "43.53",
    "age": "8",
    "points": "310",
    "timeStandard": "2020-2024 B",
    "meet": "2023 NT LAC Spooky Splash Intrasquad Meet",
    "lsc": "NT",
    "team": "Lakeside Aquatic Club",
    "swimDate": "10/22/2023",
    "competitionYear": "2024"
  },
  {
    "event": "100 BK SCY",
    "swimTime": "1:31.05",
    "age": "9",
    "points": "361",
    "timeStandard": "2020-2024 B",
    "meet": "2024 NT LAC May Madness Meet",
    "lsc": "NT",
    "team": "Lakeside Aquatic Club",
    "swimDate": "05/05/2024",
    "competitionYear": "2024"
  },
  {
    "event": "100 BK SCY",
    "swimTime": "1:31.37",
    "age": "9",
    "points": "355",
    "timeStandard": "2020-2024 B",
    "meet": "2024 NT LAC Heart Racer",
    "lsc": "NT",
    "team": "Lakeside Aquatic Club",
    "swimDate": "02/04/2024",
    "competitionYear": "2024"
  },
  {
    "event": "100 BK SCY",
    "swimTime": "1:33.48",
    "age": "8",
    "points": "312",
    "timeStandard": "2020-2024 B",
    "meet": "2023 NT LAC Spooky Splash Intrasquad Meet",
    "lsc": "NT",
    "team": "Lakeside Aquatic Club",
    "swimDate": "10/21/2023",
    "competitionYear": "2024"
  },
  {
    "event": "100 BK SCY",
    "swimTime": "1:33.82",
    "age": "9",
    "points": "305",
    "timeStandard": "2020-2024 B",
    "meet": "2024 NT LAC Ice Breaker",
    "lsc": "NT",
    "team": "Lakeside Aquatic Club",
    "swimDate": "01/07/2024",
    "competitionYear": "2024"
  },
  {
    "event": "50 BR SCY",
    "swimTime": "48.88",
    "age": "8",
    "points": "315",
    "timeStandard": "2020-2024 B",
    "meet": "2023 NT LAC Jingle Bell Meet",
    "lsc": "NT",
    "team": "Lakeside Aquatic Club",
    "swimDate": "12/09/2023",
    "competitionYear": "2024"
  },
  {
    "event": "50 BR SCY",
    "swimTime": "49.22",
    "age": "9",
    "points": "302",
    "timeStandard": "2020-2024 B",
    "meet": "2024 NT LAC Season Opener",
    "lsc": "NT",
    "team": "Lakeside Aquatic Club",
    "swimDate": "04/13/2024",
    "competitionYear": "2024"
  },
  {
    "event": "50 BR SCY",
    "swimTime": "49.46",
    "age": "9",
    "points": "293",
    "timeStandard": "2020-2024 B",
    "meet": "2024 NT LAC Ice Breaker",
    "lsc": "NT",
    "team": "Lakeside Aquatic Club",
    "swimDate": "01/06/2024",
    "competitionYear": "2024"
  },
  {
    "event": "100 BR SCY",
    "swimTime": "1:44.58",
    "age": "9",
    "points": "369",
    "timeStandard": "2020-2024 B",
    "meet": "2024 NT LAC May Madness Meet",
    "lsc": "NT",
    "team": "Lakeside Aquatic Club",
    "swimDate": "05/05/2024",
    "competitionYear": "2024"
  },
  {
    "event": "100 BR SCY",
    "swimTime": "1:45.22",
    "age": "9",
    "points": "358",
    "timeStandard": "2020-2024 B",
    "meet": "2024 NT LAC Season Opener",
    "lsc": "NT",
    "team": "Lakeside Aquatic Club",
    "swimDate": "04/14/2024",
    "competitionYear": "2024"
  },
  {
    "event": "100 BR SCY",
    "swimTime": "1:49.72",
    "age": "8",
    "points": "280",
    "timeStandard": "2020-2024 B",
    "meet": "2023 NT LAC Spooky Splash Intrasquad Meet",
    "lsc": "NT",
    "team": "Lakeside Aquatic Club",
    "swimDate": "10/21/2023",
    "competitionYear": "2024"
  },
  {
    "event": "100 BR SCY",
    "swimTime": "1:51.04",
    "age": "8",
    "points": "258",
    "timeStandard": "2020-2024 B",
    "meet": "2023 NT LAC Jingle Bell Meet",
    "lsc": "NT",
    "team": "Lakeside Aquatic Club",
    "swimDate": "12/10/2023",
    "competitionYear": "2024"
  },
  {
    "event": "100 BR SCY",
    "swimTime": "1:51.49",
    "age": "9",
    "points": "251",
    "timeStandard": "2020-2024 B",
    "meet": "2024 NT LAC Ice Breaker",
    "lsc": "NT",
    "team": "Lakeside Aquatic Club",
    "swimDate": "01/07/2024",
    "competitionYear": "2024"
  },
  {
    "event": "100 BR SCY",
    "swimTime": "1:52.51",
    "age": "9",
    "points": "235",
    "timeStandard": "2020-2024 B",
    "meet": "2024 NT LAC Heart Racer",
    "lsc": "NT",
    "team": "Lakeside Aquatic Club",
    "swimDate": "02/04/2024",
    "competitionYear": "2024"
  },
  {
    "event": "50 FL SCY",
    "swimTime": "46.05",
    "age": "9",
    "points": "115",
    "timeStandard": "Slower than B",
    "meet": "2024 NT LAC Heart Racer",
    "lsc": "NT",
    "team": "Lakeside Aquatic Club",
    "swimDate": "02/04/2024",
    "competitionYear": "2024"
  },
  {
    "event": "50 FL SCY",
    "swimTime": "47.40",
    "age": "8",
    "points": "75",
    "timeStandard": "Slower than B",
    "meet": "2023 NT LAC Jingle Bell Meet",
    "lsc": "NT",
    "team": "Lakeside Aquatic Club",
    "swimDate": "12/10/2023",
    "competitionYear": "2024"
  },
  {
    "event": "100 IM SCY",
    "swimTime": "1:38.10",
    "age": "9",
    "points": "205",
    "timeStandard": "2020-2024 B",
    "meet": "2024 NT LAC Ice Breaker",
    "lsc": "NT",
    "team": "Lakeside Aquatic Club",
    "swimDate": "01/07/2024",
    "competitionYear": "2024"
  },
  {
    "event": "100 IM SCY",
    "swimTime": "1:41.34",
    "age": "8",
    "points": "152",
    "timeStandard": "Slower than B",
    "meet": "2023 NT LAC Spooky Splash Intrasquad Meet",
    "lsc": "NT",
    "team": "Lakeside Aquatic Club",
    "swimDate": "10/21/2023",
    "competitionYear": "2024"
  },
  {
    "event": "200 IM SCY",
    "swimTime": "3:22.30",
    "age": "9",
    "points": "276",
    "timeStandard": "2020-2024 B",
    "meet": "2024 NT LAC Heart Racer",
    "lsc": "NT",
    "team": "Lakeside Aquatic Club",
    "swimDate": "02/02/2024",
    "competitionYear": "2024"
  },
  {
    "event": "50 FR LCM",
    "swimTime": "40.16",
    "age": "9",
    "points": "451",
    "timeStandard": "2020-2024 B",
    "meet": "2024 NT LAC Fun in the Sun",
    "lsc": "NT",
    "team": "Lakeside Aquatic Club",
    "swimDate": "07/06/2024",
    "competitionYear": "2024"
  },
  {
    "event": "100 FR LCM",
    "swimTime": "1:30.02",
    "age": "9",
    "points": "369",
    "timeStandard": "2020-2024 BB",
    "meet": "2024 NT LAC Fun in the Sun",
    "lsc": "NT",
    "team": "Lakeside Aquatic Club",
    "swimDate": "07/07/2024",
    "competitionYear": "2024"
  },
  {
    "event": "50 BK LCM",
    "swimTime": "47.46",
    "age": "9",
    "points": "399",
    "timeStandard": "2020-2024 BB",
    "meet": "2024 NT LAC Fun in the Sun",
    "lsc": "NT",
    "team": "Lakeside Aquatic Club",
    "swimDate": "07/06/2024",
    "competitionYear": "2024"
  },
  {
    "event": "100 BK LCM",
    "swimTime": "1:38.97",
    "age": "9",
    "points": "478",
    "timeStandard": "2020-2024 BB",
    "meet": "2024 NT LAC Fun in the Sun",
    "lsc": "NT",
    "team": "Lakeside Aquatic Club",
    "swimDate": "07/07/2024",
    "competitionYear": "2024"
  },
  {
    "event": "50 BR LCM",
    "swimTime": "53.13",
    "age": "9",
    "points": "439",
    "timeStandard": "2020-2024 BB",
    "meet": "2024 NT LAC Fun in the Sun",
    "lsc": "NT",
    "team": "Lakeside Aquatic Club",
    "swimDate": "07/07/2024",
    "competitionYear": "2024"
  },
  {
    "event": "100 BR LCM",
    "swimTime": "1:55.29",
    "age": "9",
    "points": "456",
    "timeStandard": "2020-2024 BB",
    "meet": "2024 NT LAC Fun in the Sun",
    "lsc": "NT",
    "team": "Lakeside Aquatic Club",
    "swimDate": "07/06/2024",
    "competitionYear": "2024"
  },
  {
    "event": "50 FR SCY",
    "swimTime": "39.03",
    "age": "8",
    "points": "258",
    "timeStandard": "Slower than B",
    "meet": "2023 NT LAC Summer Sweater",
    "lsc": "NT",
    "team": "Lakeside Aquatic Club",
    "swimDate": "07/22/2023",
    "competitionYear": "2023"
  },
  {
    "event": "50 FR SCY",
    "swimTime": "41.97",
    "age": "8",
    "points": "131",
    "timeStandard": "Slower than B",
    "meet": "2023 NT LAC Summer Sizzler",
    "lsc": "NT",
    "team": "Lakeside Aquatic Club",
    "swimDate": "06/03/2023",
    "competitionYear": "2023"
  },
  {
    "event": "100 FR SCY",
    "swimTime": "1:24.62",
    "age": "8",
    "points": "246",
    "timeStandard": "2020-2024 B",
    "meet": "2023 NT LAC Summer Sweater",
    "lsc": "NT",
    "team": "Lakeside Aquatic Club",
    "swimDate": "07/21/2023",
    "competitionYear": "2023"
  },
  {
    "event": "100 FR SCY",
    "swimTime": "1:30.79",
    "age": "8",
    "points": "128",
    "timeStandard": "Slower than B",
    "meet": "2023 NT LAC Summer Sizzler",
    "lsc": "NT",
    "team": "Lakeside Aquatic Club",
    "swimDate": "06/02/2023",
    "competitionYear": "2023"
  },
  {
    "event": "50 BK SCY",
    "swimTime": "43.07",
    "age": "8",
    "points": "330",
    "timeStandard": "2020-2024 B",
    "meet": "2023 NT LAC Summer Sweater",
    "lsc": "NT",
    "team": "Lakeside Aquatic Club",
    "swimDate": "07/21/2023",
    "competitionYear": "2023"
  },
  {
    "event": "50 BK SCY",
    "swimTime": "48.14",
    "age": "8",
    "points": "135",
    "timeStandard": "Slower than B",
    "meet": "2023 NT LAC Summer Sizzler",
    "lsc": "NT",
    "team": "Lakeside Aquatic Club",
    "swimDate": "06/02/2023",
    "competitionYear": "2023"
  },
  {
    "event": "100 BK SCY",
    "swimTime": "1:48.63",
    "age": "8",
    "points": "65",
    "timeStandard": "Slower than B",
    "meet": "2023 NT LAC Summer Sizzler",
    "lsc": "NT",
    "team": "Lakeside Aquatic Club",
    "swimDate": "06/03/2023",
    "competitionYear": "2023"
  },
  {
    "event": "50 BR SCY",
    "swimTime": "54.93",
    "age": "8",
    "points": "115",
    "timeStandard": "Slower than B",
    "meet": "2023 NT LAC Summer Sweater",
    "lsc": "NT",
    "team": "Lakeside Aquatic Club",
    "swimDate": "07/21/2023",
    "competitionYear": "2023"
  },
  {
    "event": "50 FL SCY",
    "swimTime": "52.52",
    "age": "8",
    "points": "1",
    "timeStandard": "Slower than B",
    "meet": "2023 NT LAC Summer Sweater",
    "lsc": "NT",
    "team": "Lakeside Aquatic Club",
    "swimDate": "07/22/2023",
    "competitionYear": "2023"
  },
  {
    "event": "50 FL SCY",
    "swimTime": "57.64",
    "age": "8",
    "points": "1",
    "timeStandard": "Slower than B",
    "meet": "2023 NT LAC Summer Sizzler",
    "lsc": "NT",
    "team": "Lakeside Aquatic Club",
    "swimDate": "06/03/2023",
    "competitionYear": "2023"
  },
  {
    "event": "100 IM SCY",
    "swimTime": "1:42.88",
    "age": "8",
    "points": "129",
    "timeStandard": "Slower than B",
    "meet": "2023 NT LAC Summer Sweater",
    "lsc": "NT",
    "team": "Lakeside Aquatic Club",
    "swimDate": "07/22/2023",
    "competitionYear": "2023"
  }
]