[
  {
    "event": "50 FR SCY",
    "swimTime": "38.82",
    "age": "12",
    "points": "2",
    "timeStandard": "Slower than B",
    "meet": "2024 CA CANY Cranberry Classic",
    "lsc": "CA",
    "team": "CLASS Aquatics",
    "swimDate": "11/23/2024",
    "competitionYear": "-1"
  },
  {
    "event": "50 FR SCY",
    "swimTime": "39.67",
    "age": "12",
    "points": "1",
    "timeStandard": "Slower than B",
    "meet": "2024 CA CLSS Holiday Coastal WInter Championships",
    "lsc": "CA",
    "team": "CLASS Aquatics",
    "swimDate": "12/07/2024",
    "competitionYear": "-1"
  },
  {
    "event": "100 BK SCY",
    "swimTime": "1:45.16",
    "age": "12",
    "points": "1",
    "timeStandard": "Slower than B",
    "meet": "2024 CA CANY Cranberry Classic",
    "lsc": "CA",
    "team": "CLASS Aquatics",
    "swimDate": "11/23/2024",
    "competitionYear": "-1"
  },
  {
    "event": "100 BK SCY",
    "swimTime": "1:52.08",
    "age": "12",
    "points": "1",
    "timeStandard": "Slower than B",
    "meet": "2024 CA CLSS Holiday Coastal WInter Championships",
    "lsc": "CA",
    "team": "CLASS Aquatics",
    "swimDate": "12/07/2024",
    "competitionYear": "-1"
  },
  {
    "event": "50 BR SCY",
    "swimTime": "51.03",
    "age": "12",
    "points": "1",
    "timeStandard": "Slower than B",
    "meet": "2024 CA CANY Cranberry Classic",
    "lsc": "CA",
    "team": "CLASS Aquatics",
    "swimDate": "11/23/2024",
    "competitionYear": "-1"
  },
  {
    "event": "50 FR LCM",
    "swimTime": "48.14",
    "age": "12",
    "points": "1",
    "timeStandard": "Slower than B",
    "meet": "2024 CA CLSS Memorial Day",
    "lsc": "CA",
    "team": "CLASS Aquatics",
    "swimDate": "05/25/2024",
    "competitionYear": "-1"
  },
  {
    "event": "100 BK LCM",
    "swimTime": "2:03.74",
    "age": "12",
    "points": "1",
    "timeStandard": "Slower than B",
    "meet": "2024 CA CLSS Memorial Day",
    "lsc": "CA",
    "team": "CLASS Aquatics",
    "swimDate": "05/25/2024",
    "competitionYear": "-1"
  },
  {
    "event": "50 BR LCM",
    "swimTime": "1:03.99",
    "age": "12",
    "points": "1",
    "timeStandard": "Slower than B",
    "meet": "2024 CA CLSS Memorial Day",
    "lsc": "CA",
    "team": "CLASS Aquatics",
    "swimDate": "05/25/2024",
    "competitionYear": "-1"
  },
  {
    "event": "50 FR SCY",
    "swimTime": "38.82",
    "age": "12",
    "points": "2",
    "timeStandard": "Slower than B",
    "meet": "2024 CA CANY Cranberry Classic",
    "lsc": "CA",
    "team": "CLASS Aquatics",
    "swimDate": "11/23/2024",
    "competitionYear": "2025"
  },
  {
    "event": "50 FR SCY",
    "swimTime": "39.67",
    "age": "12",
    "points": "1",
    "timeStandard": "Slower than B",
    "meet": "2024 CA CLSS Holiday Coastal WInter Championships",
    "lsc": "CA",
    "team": "CLASS Aquatics",
    "swimDate": "12/07/2024",
    "competitionYear": "2025"
  },
  {
    "event": "100 BK SCY",
    "swimTime": "1:45.16",
    "age": "12",
    "points": "1",
    "timeStandard": "Slower than B",
    "meet": "2024 CA CANY Cranberry Classic",
    "lsc": "CA",
    "team": "CLASS Aquatics",
    "swimDate": "11/23/2024",
    "competitionYear": "2025"
  },
  {
    "event": "100 BK SCY",
    "swimTime": "1:52.08",
    "age": "12",
    "points": "1",
    "timeStandard": "Slower than B",
    "meet": "2024 CA CLSS Holiday Coastal WInter Championships",
    "lsc": "CA",
    "team": "CLASS Aquatics",
    "swimDate": "12/07/2024",
    "competitionYear": "2025"
  },
  {
    "event": "50 BR SCY",
    "swimTime": "51.03",
    "age": "12",
    "points": "1",
    "timeStandard": "Slower than B",
    "meet": "2024 CA CANY Cranberry Classic",
    "lsc": "CA",
    "team": "CLASS Aquatics",
    "swimDate": "11/23/2024",
    "competitionYear": "2025"
  },
  {
    "event": "50 FR LCM",
    "swimTime": "48.14",
    "age": "12",
    "points": "1",
    "timeStandard": "Slower than B",
    "meet": "2024 CA CLSS Memorial Day",
    "lsc": "CA",
    "team": "CLASS Aquatics",
    "swimDate": "05/25/2024",
    "competitionYear": "2024"
  },
  {
    "event": "100 BK LCM",
    "swimTime": "2:03.74",
    "age": "12",
    "points": "1",
    "timeStandard": "Slower than B",
    "meet": "2024 CA CLSS Memorial Day",
    "lsc": "CA",
    "team": "CLASS Aquatics",
    "swimDate": "05/25/2024",
    "competitionYear": "2024"
  },
  {
    "event": "50 BR LCM",
    "swimTime": "1:03.99",
    "age": "12",
    "points": "1",
    "timeStandard": "Slower than B",
    "meet": "2024 CA CLSS Memorial Day",
    "lsc": "CA",
    "team": "CLASS Aquatics",
    "swimDate": "05/25/2024",
    "competitionYear": "2024"
  }
]